{"cameraMode":{"drawMode":0,"name":"Shaded","section":"Shading Mode"},"sceneLighting":true,"audioPlay":false,"sceneViewState":{"showFog":true,"showMaterialUpdate":false,"showSkybox":true,"showFlares":true,"showImageEffects":true,"showParticleSystems":true},"in2DMode":false,"pivot":{"x":5.177046775817871,"y":-1.8894100189208985,"z":1.0030289888381959},"rotation":{"x":-0.6344571709632874,"y":0.002781887073069811,"z":-0.0022830346133559944,"w":-0.7729496955871582},"size":12.025718688964844,"orthographic":false}